wslpy/__init__.py
wslpy/__internal__.py
wslpy/convert.py
wslpy/exec.py
wslpy/helper.py
wslpy/system.py
wslpy/win.py
wslpy-0.0.13.dist-info/LICENSE
wslpy-0.0.13.dist-info/METADATA
wslpy-0.0.13.dist-info/WHEEL
wslpy-0.0.13.dist-info/top_level.txt
wslpy-0.0.13.dist-info/RECORD
