Metadata-Version: 2.1
Name: wslpy
Version: 0.0.13
Summary: Python Library for WSL specific tasks
Home-page: https://github.com/wslutilities/wslpy
Author: Patrick Wu
Author-email: me@patrickwu.space
License: GPLv3
Keywords: system,WSL,Windows 10,Windows 11
Platform: UNKNOWN
Classifier: Environment :: Console
Classifier: License :: OSI Approved :: GNU General Public License v3 (GPLv3)
Classifier: Operating System :: POSIX :: Linux
Classifier: Programming Language :: Python :: 3 :: Only
Requires-Dist: netifaces
